[
  {
    "id":1001,
    "message":"Appointment Delayed!",
    "seenByDoctor":true,
    "seenByPatient":true
  },
  {
    "id":1002,
    "message":"Appointment Delayed!",
    "seenByDoctor":true,
    "seenByPatient":true
  },
  {
    "id":1003,
    "message":"Appointment Delayed!",
    "seenByDoctor":true,
    "seenByPatient":true
  },
  {
    "id":1004,
    "message":"Appointment Delayed!",
    "seenByDoctor":true,
    "seenByPatient":true
  },
  {
    "id":1005,
    "message":"AppointmentDelayed!",
    "seenByDoctor":true,
    "seenByPatient":true
  }
]
